decky_remote/__init__.py
decky_remote/decky_tail_plugin_logs.py
decky_remote/decky_ws_request.py
decky_remote/ssh_rpc.py
decky_remote-0.8.0.dist-info/licenses/LICENSE
decky_remote-0.8.0.dist-info/METADATA
decky_remote-0.8.0.dist-info/WHEEL
decky_remote-0.8.0.dist-info/entry_points.txt
decky_remote-0.8.0.dist-info/top_level.txt
decky_remote-0.8.0.dist-info/RECORD
