Metadata-Version: 2.4
Name: decky-remote
Version: 0.8.0
Summary: Development tool for Decky plugins
Author: Nathan Reynolds
License: GPL-3.0-or-later
Project-URL: Repository, https://github.com/nathforge/decky-remote
Classifier: Development Status :: 4 - Beta
Classifier: Intended Audience :: Developers
Classifier: Programming Language :: Python :: 3
Classifier: Programming Language :: Python :: 3.8
Classifier: Programming Language :: Python :: 3.9
Classifier: Programming Language :: Python :: 3.10
Classifier: Programming Language :: Python :: 3.11
Classifier: Programming Language :: Python :: 3.12
Requires-Python: >=3.8
License-File: LICENSE
Requires-Dist: typer>=0.9.0
Dynamic: license-file
